{"duration": 1.2902801036834717, "input_args": {"transformer": "TfidfVectorizer(max_features=2500)", "X": "198310           highly recommended\n144123                    fabulous!\n143621                  good choice\n155755              waste of money!\n163494    did not meet expectations\n                    ...            \n123428               decent product\n154818                         fair\n148514              waste of money!\n15874              terrible product\n132908                    just okay\nName: Review, Length: 115443, dtype: object", "y": "198310    Positive\n144123    Positive\n143621    Positive\n155755    Negative\n163494    Negative\n            ...   \n123428    Negative\n154818    Negative\n148514    Negative\n15874     Negative\n132908    Negative\nName: Label, Length: 115443, dtype: object", "weight": "None", "message_clsname": "'Pipeline'", "message": "None", "**": "{}"}}